devtools_phone/__init__.py
devtools_phone-1.0.1.dist-info/METADATA
devtools_phone-1.0.1.dist-info/WHEEL
devtools_phone-1.0.1.dist-info/top_level.txt
devtools_phone-1.0.1.dist-info/RECORD
