Metadata-Version: 2.1
Name: devtools-phone
Version: 1.0.1
Summary: Phone number formatter
Home-page: https://devtools.at/tools/phone-formatter
Author: DevTools.at
Author-email: hello@devtools.at
Project-URL: Homepage, https://devtools.at/tools/phone-formatter
Project-URL: Repository, https://github.com/devtools-at/phone-formatter
Classifier: Development Status :: 4 - Beta
Classifier: Intended Audience :: Developers
Classifier: License :: OSI Approved :: MIT License
Classifier: Programming Language :: Python :: 3
Requires-Python: >=3.8
